bssolar/__init__.py
bssolar/connect.py
solarutils/__init__.py
solarutils/connect.py
bssolar-0.0.2.dist-info/METADATA
bssolar-0.0.2.dist-info/WHEEL
bssolar-0.0.2.dist-info/top_level.txt
bssolar-0.0.2.dist-info/RECORD
